[
  {
    "_id": "647c649f5c36c62a23f54841",
    "username": "Dolores Gusikowski",
    "password": "qoyezo",
    "avatar_url": "",
    "gender": "female",
    "school": {
      "code": "118988",
      "name": "Kuhic LLC"
    },
    "birthday": "2003-09-21T20:55:39.531Z",
    "historys": [
      {
        "title": "Nulla ipsum saepe sint ipsum tenetur odit.",
        "content": "Facilis corrupti impedit facere facere. Ea autem maiores vero qui repudiandae doloremque. Non libero sapiente tenetur id repudiandae nostrum. Dignissimos inventore asperiores explicabo libero aspernatur ad sed quia.",
        "date": "2022-08-25T18:52:19.491Z"
      },
      {
        "title": "Repellendus non ipsum voluptatem labore cupiditate temporibus impedit et.",
        "content": "Aut labore rerum minima quibusdam impedit et. In maiores est quasi asperiores iusto. Quasi aspernatur eos enim alias temporibus minima adipisci sequi consectetur. Aut iusto qui repellendus eligendi ut. Ipsam doloribus minima fugit recusandae delectus sed sed non.",
        "date": "2022-11-15T22:12:24.152Z"
      },
      {
        "title": "Nulla quis magni voluptatem labore.",
        "content": "Ad voluptas nesciunt et qui cumque quis autem earum. Natus unde et eos. Aut numquam consequatur laboriosam quam. Autem rerum rerum delectus tempore minus.",
        "date": "2023-05-30T19:24:27.682Z"
      },
      {
        "title": "Ut soluta adipisci neque sapiente nemo eum eveniet ex.",
        "content": "Sed numquam quasi officia. Et qui nam dolores sunt. Et et sit sapiente et tenetur repudiandae sit qui ipsa.",
        "date": "2022-10-01T11:56:09.213Z"
      },
      {
        "title": "Facilis enim placeat neque.",
        "content": "Quod ut magnam. Fuga qui distinctio fugiat ex in temporibus. Corrupti similique nihil. Facere rerum consequatur qui. Distinctio sunt rerum.",
        "date": "2022-06-26T12:36:19.161Z"
      }
    ]
  },
  {
    "_id": "647c649f5c36c62a23f54842",
    "username": "Jerome Krajcik",
    "password": "goqoda",
    "avatar_url": "",
    "gender": "male",
    "school": {
      "code": "119202",
      "name": "Kozey and Sons"
    },
    "birthday": "1995-09-06T04:50:42.318Z",
    "historys": [
      {
        "title": "Veritatis alias possimus expedita maiores sint fuga necessitatibus.",
        "content": "Voluptatum cumque architecto qui aut nihil. Et est eius adipisci sint enim iure. Architecto minus et minus. Totam ex voluptatem. Est sapiente similique eos facilis eos architecto nulla eligendi.",
        "date": "2022-12-25T03:45:24.395Z"
      },
      {
        "title": "Et rerum voluptates et et pariatur dolorum sit id.",
        "content": "Et at enim fugit consequatur sit magni quia beatae a. Ad est dolorum omnis rerum aut. Fugiat at ut doloribus repudiandae. Aut consequatur commodi.",
        "date": "2022-10-27T06:49:35.564Z"
      },
      {
        "title": "Et adipisci fugiat adipisci incidunt corrupti dolor et explicabo.",
        "content": "Alias qui ut repellat. Ut aliquam quo occaecati sed velit ea accusamus. Aut eveniet accusamus numquam nobis molestiae.",
        "date": "2023-05-07T04:28:32.592Z"
      },
      {
        "title": "Cumque rerum nihil.",
        "content": "Neque id amet quis et. Impedit cum repellat ut ipsa quia aliquid fuga veniam suscipit. Deserunt atque quis necessitatibus. Eos a mollitia est asperiores. Qui doloremque nihil quos iure quae non odit.",
        "date": "2022-08-30T23:06:48.750Z"
      },
      {
        "title": "Quidem assumenda est amet optio est error adipisci.",
        "content": "Impedit blanditiis aut velit. Laboriosam vitae qui nisi et enim cumque in quam facilis. Aliquid amet consequatur officia amet ratione adipisci velit et quis.",
        "date": "2022-10-25T22:27:52.378Z"
      }
    ]
  },
  {
    "_id": "647c649f5c36c62a23f54843",
    "username": "Darrel McDermott",
    "password": "yuxahu",
    "avatar_url": "",
    "gender": "female",
    "school": {
      "code": "116986",
      "name": "Cummerata Group"
    },
    "birthday": "2000-03-23T04:43:53.802Z",
    "historys": [
      {
        "title": "Ea eum dicta et aspernatur animi at.",
        "content": "Nobis eius at debitis veniam et consequatur et. Laborum numquam assumenda et aperiam ea distinctio. Repudiandae sint aliquid. Natus sed facere cupiditate saepe quia eum et.",
        "date": "2023-05-12T19:40:30.101Z"
      },
      {
        "title": "Suscipit laboriosam et pariatur at sapiente nulla quam ex sunt.",
        "content": "Quia amet magnam quibusdam. Est non enim sapiente necessitatibus numquam. Ipsa illum cupiditate eum odit sunt distinctio in voluptate.",
        "date": "2022-10-18T06:17:03.905Z"
      },
      {
        "title": "Perspiciatis eos qui perspiciatis ab laboriosam facilis qui.",
        "content": "Vel occaecati ad corrupti sit. Dolor repellat temporibus sunt et aperiam a at. Quaerat molestiae voluptatem. Non eum id voluptatibus ut non qui soluta. Vel cupiditate aut aliquam. Repellat quis dolores et porro qui rem maiores.",
        "date": "2023-02-06T16:24:48.830Z"
      },
      {
        "title": "Officia quia occaecati accusamus dolorem vero quis harum nobis ad.",
        "content": "Quod consequatur iusto omnis impedit magni officiis. Nam accusamus ut aut sit a. Voluptatem alias quia inventore accusamus suscipit. Provident aut distinctio et unde rerum sunt cupiditate inventore aut. Nulla illo atque pariatur officiis architecto facere cupiditate.",
        "date": "2022-09-25T11:19:55.786Z"
      },
      {
        "title": "Sequi esse officia voluptas dolorem voluptatem commodi.",
        "content": "Sequi laboriosam officia corrupti. Ab cumque ut repellendus pariatur minima. Vel laboriosam sint maxime deserunt ut molestias rem aut. Similique soluta ratione officia.",
        "date": "2022-08-21T00:41:13.896Z"
      }
    ]
  },
  {
    "_id": "647c649f5c36c62a23f54844",
    "username": "Darla Koch",
    "password": "facuma",
    "avatar_url": "",
    "gender": "male",
    "school": {
      "code": "117055",
      "name": "Farrell - Gutkowski"
    },
    "birthday": "2002-02-24T01:16:57.981Z",
    "historys": [
      {
        "title": "Dolorem debitis omnis.",
        "content": "Voluptatem repellendus necessitatibus deleniti asperiores. Qui totam temporibus veniam ab est. Quisquam similique eos quas excepturi. Consequuntur maxime harum possimus aperiam. Ea voluptatum quis deleniti assumenda.",
        "date": "2022-06-13T19:55:44.903Z"
      },
      {
        "title": "Sapiente et voluptatem explicabo totam non at.",
        "content": "Numquam ut aut recusandae suscipit repudiandae vero. Ducimus voluptas et. Repudiandae odit perferendis in qui deserunt in. Dignissimos nobis est corporis. Dolores ratione inventore est voluptas. At distinctio et fugit modi necessitatibus similique et sed et.",
        "date": "2023-05-31T03:25:13.130Z"
      },
      {
        "title": "Voluptates quaerat dolor voluptas enim omnis.",
        "content": "Non labore aut sequi sint placeat ut. Qui deleniti neque recusandae. Pariatur molestias totam explicabo rem et id in. Id sapiente ut molestias eligendi eum odit recusandae voluptatum non. Consequuntur sunt natus voluptas et hic esse quo rerum.",
        "date": "2022-06-14T22:24:44.865Z"
      },
      {
        "title": "Ipsam modi enim expedita consequatur hic quisquam asperiores.",
        "content": "Expedita accusamus et reprehenderit pariatur magni. Rerum nisi voluptates quod. Minima officiis sit veniam esse in quia. Et possimus natus error ut. Ut consequatur perspiciatis illo ipsa quod maxime eius.",
        "date": "2022-12-09T13:46:12.917Z"
      },
      {
        "title": "Eligendi perferendis sed.",
        "content": "Deleniti aut consequuntur dolores quaerat explicabo aliquid unde ut autem. Adipisci aut delectus assumenda. Officia consequuntur neque quis doloremque.",
        "date": "2022-12-21T07:30:43.789Z"
      }
    ]
  },
  {
    "_id": "647c649f5c36c62a23f54845",
    "username": "Faye Berge",
    "password": "jewomu",
    "avatar_url": "",
    "gender": "female",
    "school": {
      "code": "119776",
      "name": "Becker, Stanton and Hegmann"
    },
    "birthday": "1999-02-17T09:26:25.351Z",
    "historys": [
      {
        "title": "Doloremque fugit repellat repellendus.",
        "content": "Rem asperiores est et id amet aut suscipit. Quis quaerat repellat. Voluptas quam architecto ullam laborum. Qui rem eum voluptate voluptates earum eligendi fugit commodi debitis. Dicta ab molestias temporibus ut aperiam corporis perferendis repudiandae cupiditate. In natus voluptatem sit officiis.",
        "date": "2023-01-18T15:39:13.353Z"
      },
      {
        "title": "Quidem dolorem dicta veniam.",
        "content": "Voluptas sint et tempora reiciendis culpa ea perferendis a velit. Velit fugit eum placeat id voluptatum ullam at animi. Quia est fugiat est autem distinctio aut omnis ut. Debitis est nihil corporis quia sapiente voluptas et amet consequatur.",
        "date": "2022-06-16T05:34:26.303Z"
      },
      {
        "title": "Delectus odio inventore totam quod aut voluptas doloremque.",
        "content": "Voluptas veritatis veniam et. Dolor et et velit esse quo. Quasi deleniti eum aliquam nihil aut amet cum. Consequuntur blanditiis dignissimos dolore accusantium ipsum voluptatum. Laudantium qui voluptas. Architecto sint quas.",
        "date": "2023-01-06T10:02:46.817Z"
      },
      {
        "title": "Est aut voluptates autem.",
        "content": "Fuga non perspiciatis possimus molestiae quo possimus possimus quo. Dolore reiciendis quas sapiente nihil pariatur illum aut. Rerum at cupiditate dolor et aut. Aliquid inventore repudiandae. Magni excepturi qui eveniet nesciunt sapiente.",
        "date": "2023-05-23T07:46:58.306Z"
      },
      {
        "title": "Ut distinctio aspernatur ipsa voluptatum fugit molestiae illo sunt sunt.",
        "content": "Cum sunt et dolore. Dolorem sint natus tempore adipisci voluptas commodi omnis eum. Molestias similique amet qui neque.",
        "date": "2022-12-22T03:06:30.159Z"
      }
    ]
  },
  {
    "_id": "647c649f5c36c62a23f54846",
    "username": "Reginald Moen",
    "password": "vohoba",
    "avatar_url": "",
    "gender": "female",
    "school": {
      "code": "115980",
      "name": "Lang Group"
    },
    "birthday": "1998-07-30T13:22:24.357Z",
    "historys": [
      {
        "title": "Cum qui voluptas doloremque.",
        "content": "Iure nihil aut est. Inventore et quia. Officia voluptas eum consequatur eaque.",
        "date": "2023-05-10T13:43:50.685Z"
      },
      {
        "title": "Vero sit alias natus rerum sit et rerum esse ea.",
        "content": "Vel totam assumenda nihil officia illum cumque. Quo sunt quibusdam doloremque dolores. Non cum nemo deserunt ut. Veniam placeat suscipit sunt magni eum eum esse. Optio facilis ut natus officiis explicabo.",
        "date": "2022-09-21T23:19:18.307Z"
      },
      {
        "title": "Ut ea accusamus repellat veniam ut dicta blanditiis.",
        "content": "Exercitationem quis vel eligendi reprehenderit rerum rerum voluptas mollitia deserunt. Facere vero voluptates sunt qui et esse voluptatem. Possimus itaque ducimus eius asperiores.",
        "date": "2023-01-11T15:36:38.899Z"
      },
      {
        "title": "Ut error et nesciunt maxime voluptas voluptas qui voluptatem.",
        "content": "Voluptatem ipsam voluptas vitae labore eius sint. Voluptatum voluptatem et qui accusamus eveniet quaerat aspernatur dolor non. Ducimus et et voluptatem voluptatem quae vel quas voluptatem aut. Asperiores non eligendi illum nihil eveniet.",
        "date": "2022-06-15T04:44:57.749Z"
      },
      {
        "title": "Sit sint eius.",
        "content": "Modi impedit dolor quis vitae repudiandae sed consequuntur qui. Iure nihil cumque et sit consectetur enim eum nemo pariatur. Magni hic quasi et facere qui.",
        "date": "2023-02-08T15:02:33.584Z"
      }
    ]
  },
  {
    "_id": "647c649f5c36c62a23f54847",
    "username": "Dr. Barry Wisoky",
    "password": "yuqizu",
    "avatar_url": "",
    "gender": "female",
    "school": {
      "code": "112555",
      "name": "Fadel - Hoppe"
    },
    "birthday": "1997-02-12T01:31:52.167Z",
    "historys": [
      {
        "title": "Laboriosam dolor quo hic consectetur in illo occaecati.",
        "content": "Quisquam possimus eum aliquam dignissimos non. Tempora explicabo voluptatem quod occaecati. Quis voluptatem et quae quia neque. Odio distinctio necessitatibus voluptatem alias. Repellendus voluptate tempore necessitatibus.",
        "date": "2022-08-11T03:59:14.476Z"
      },
      {
        "title": "Qui dolorem non quibusdam tempora.",
        "content": "Pariatur quis aut illo. Numquam autem architecto nemo repellat sit modi aliquid aut. Veritatis aliquid eligendi earum magnam inventore et eos quisquam libero. Ea dolor et sed. Eum vel ut exercitationem et asperiores sequi et. Ad eaque non quaerat qui.",
        "date": "2022-08-05T09:19:21.407Z"
      },
      {
        "title": "Et quia veniam eos iure et dolores.",
        "content": "Numquam autem suscipit beatae molestias. Quas dolores unde est rem accusantium vitae delectus modi dolor. Est natus accusantium et nisi reprehenderit officia. Voluptatem qui deleniti dignissimos ut repudiandae. Blanditiis iusto ipsam fugit est nesciunt sequi reprehenderit magni eveniet. Nulla qui est illo consequuntur.",
        "date": "2022-12-05T14:46:46.638Z"
      },
      {
        "title": "Corrupti ut assumenda.",
        "content": "Maxime voluptatem et et consequatur ut omnis voluptatum. Impedit veritatis reiciendis accusantium iure deserunt error repellendus veritatis. Ea aut nulla placeat beatae consequatur eius earum corrupti.",
        "date": "2022-12-21T00:28:45.663Z"
      },
      {
        "title": "Quibusdam est et doloribus ullam aut ullam eum consectetur soluta.",
        "content": "Vel laboriosam necessitatibus natus aut dolorem similique tempora minus. Commodi non quia maxime quis et ipsam. Consectetur reiciendis in nostrum tenetur labore dolore nobis ut odio. Officia suscipit quia repellendus id.",
        "date": "2022-12-03T16:51:17.357Z"
      }
    ]
  },
  {
    "_id": "647c649f5c36c62a23f54848",
    "username": "Traci Halvorson",
    "password": "qirubi",
    "avatar_url": "",
    "gender": "male",
    "school": {
      "code": "111952",
      "name": "Raynor - Hodkiewicz"
    },
    "birthday": "1998-04-24T06:11:33.012Z",
    "historys": [
      {
        "title": "Et esse debitis est voluptatem sunt quibusdam.",
        "content": "Nostrum ut nihil consequuntur illo ea. Et ipsum dicta est voluptatem aut sint velit. Placeat culpa voluptatum odit. Similique officiis commodi hic dolorem assumenda non. Fugiat qui accusantium labore non.",
        "date": "2022-11-02T02:25:51.239Z"
      },
      {
        "title": "Laborum et suscipit libero quas eum et nam minima quibusdam.",
        "content": "Odit reiciendis necessitatibus enim ullam pariatur dolores. Praesentium nam maiores reiciendis et qui voluptatem quisquam illum laborum. In corrupti et molestiae illo praesentium totam et aut.",
        "date": "2022-10-02T00:45:30.702Z"
      },
      {
        "title": "Et officiis ut eum repudiandae veniam dicta.",
        "content": "Est consectetur ex. Excepturi similique et facilis. Praesentium laboriosam placeat culpa. Quaerat et possimus et dolores dignissimos. Voluptas ut dolorem voluptas non accusantium ea laborum. Earum tenetur ipsum ipsam.",
        "date": "2022-12-16T18:44:08.076Z"
      },
      {
        "title": "Eius porro voluptatibus fugit.",
        "content": "Voluptatibus nisi rem ut. Et at neque sint accusamus. Corrupti repudiandae rerum autem ut et rerum porro. Inventore repudiandae assumenda. Dolorum tenetur deserunt non autem et et voluptatem. Accusantium iusto eum dolor vel assumenda repellat est.",
        "date": "2023-04-26T14:38:46.974Z"
      },
      {
        "title": "Autem voluptatibus quis illo.",
        "content": "Excepturi sit ut. Qui qui officia dolorum labore ut illum quia. Aperiam eum a. Omnis maxime enim. Nobis dolor totam saepe at odio voluptatibus veritatis et est. Adipisci quis et possimus velit voluptas aut.",
        "date": "2023-04-29T15:52:33.320Z"
      }
    ]
  },
  {
    "_id": "647c649f5c36c62a23f54849",
    "username": "Abel VonRueden",
    "password": "sabixa",
    "avatar_url": "",
    "gender": "male",
    "school": {
      "code": "118866",
      "name": "Schulist, Vandervort and Marquardt"
    },
    "birthday": "2000-11-14T13:30:08.844Z",
    "historys": [
      {
        "title": "Quam fugit animi id impedit praesentium.",
        "content": "Voluptatibus officiis earum et sit ipsam quo. Ullam vitae enim sequi porro et dolor asperiores eius ut. Labore ducimus unde voluptatum. Dolorum earum molestias officia quo optio doloribus atque officiis nulla. Aliquid autem officia perferendis saepe iusto.",
        "date": "2022-08-07T07:19:39.899Z"
      },
      {
        "title": "Nesciunt laborum consequatur sed molestias exercitationem occaecati itaque.",
        "content": "Repellendus aut labore vero velit sunt aut alias assumenda quia. Libero impedit assumenda facilis. In accusantium impedit aut est ex reprehenderit quod id aliquid.",
        "date": "2023-01-01T00:45:56.958Z"
      },
      {
        "title": "Non tempore excepturi.",
        "content": "Quis fugiat voluptates nesciunt dignissimos tempore. Est aut officiis accusantium tenetur debitis expedita. Ad molestiae iste optio dolor qui dolore fuga sunt aut. Explicabo deserunt ut aspernatur laborum non expedita saepe dolor temporibus.",
        "date": "2022-09-30T14:16:35.690Z"
      },
      {
        "title": "Nemo voluptatem unde aliquid aut veritatis veniam et.",
        "content": "Velit libero dolore. Beatae doloribus non. Cum similique dolore quidem culpa. Perspiciatis harum ut ipsa.",
        "date": "2022-09-25T19:44:09.943Z"
      },
      {
        "title": "Ut dignissimos et nulla id nihil culpa ratione.",
        "content": "Officia rerum sequi quae repudiandae nisi labore accusantium est. Quisquam animi omnis animi similique enim ab voluptate quo. At quo consequatur quis et in hic dolorem non accusantium.",
        "date": "2023-02-08T15:39:50.252Z"
      }
    ]
  },
  {
    "_id": "647c649f5c36c62a23f5484a",
    "username": "Freda Hessel",
    "password": "hizoxi",
    "avatar_url": "",
    "gender": "male",
    "school": {
      "code": "110167",
      "name": "Denesik, Macejkovic and Heaney"
    },
    "birthday": "1997-07-21T04:58:13.851Z",
    "historys": [
      {
        "title": "Debitis veniam ut nobis.",
        "content": "Occaecati sed incidunt alias ut distinctio. Recusandae voluptatibus maxime. Autem laboriosam ex. Ut consectetur voluptatem voluptatem nostrum officia similique.",
        "date": "2023-01-30T18:05:07.102Z"
      },
      {
        "title": "Eos est ipsam iusto hic ipsa excepturi et cumque.",
        "content": "Minus voluptas rerum minima harum. Quia explicabo qui odit voluptatem soluta. Omnis quis maxime rem soluta quisquam omnis molestiae libero. Esse voluptatem perspiciatis saepe dolores corrupti. Unde dicta repellat impedit voluptates dolorem repellat qui sed. Esse consequatur quod placeat qui labore autem maiores qui.",
        "date": "2023-01-01T22:03:35.265Z"
      },
      {
        "title": "Et nihil dolor.",
        "content": "Fuga natus eius ut amet autem nostrum et ut accusantium. Sed suscipit velit asperiores nihil. Autem sed voluptatem rem. Consequatur sed ipsum. Et consequuntur tempore porro neque dolorem. Voluptatibus consequuntur et ducimus aut odit voluptatibus facere ut quod.",
        "date": "2023-05-26T03:36:30.365Z"
      },
      {
        "title": "Qui mollitia quos tempora ipsum placeat fugit.",
        "content": "Assumenda iure rerum impedit dolor et. Ipsam ab placeat. Eos ea qui nemo. Quia reprehenderit numquam esse voluptatibus.",
        "date": "2023-02-06T16:24:05.563Z"
      },
      {
        "title": "Enim aut optio eaque esse deserunt est nihil sapiente.",
        "content": "Architecto nisi dicta quas quos. Exercitationem quas minima voluptatem quia. A ducimus et odit in exercitationem temporibus enim ipsum atque.",
        "date": "2023-04-28T15:05:02.263Z"
      }
    ]
  }
]